{
    "connection-id": "localhost",
    "version": "0.5.4",
    "query": "\nSELECT c_1.* FROM \"tenant\" AS \"t_0\" JOIN \"company\" AS \"c_1\" ON \"c_1\".\"tenantId\" = \"t_0\".\"id\" WHERE \"c_1\".\"name\" = 'Acme Inc' LIMIT 2;\n",
    "state": {
        "hints": {
            "table": []
        },
        "table-count": 2,
        "where": [
            [
                "c_1",
                "name",
                "=",
                "Acme Inc"
            ]
        ],
        "selected-tables": [
            {
                "schema": null,
                "table": "tenant",
                "alias": "t_0"
            },
            {
                "schema": null,
                "table": "company",
                "alias": "c_1"
            }
        ],
        "limit": 2,
        "pending-count": 0,
        "columns": [],
        "operation": {
            "type": "limit",
            "value": 2
        },
        "joins": {
            "t_0": {
                "c_1": [
                    "c_1",
                    "tenantId",
                    "=",
                    "t_0",
                    "id"
                ]
            }
        },
        "tables": [
            {
                "schema": null,
                "table": "tenant",
                "alias": "t_0"
            },
            {
                "schema": null,
                "table": "company",
                "alias": "c_1"
            }
        ],
        "context": "c_1",
        "connection-id": "default",
        "aliases": {
            "t_0": {
                "table": "tenant",
                "schema": null
            },
            "c_1": {
                "table": "company",
                "schema": null
            }
        }
    },
    "deprecation-notice": "Properties will be removed in the next major version: `hints`, `context`. Use `state` (`hints`, `selected-tables`) instead.",
    "hints": {
        "table": []
    },
    "context": [
        {
            "schema": null,
            "table": "tenant",
            "alias": "t_0"
        },
        {
            "schema": null,
            "table": "company",
            "alias": "c_1"
        }
    ]
}
